<?xml version="1.0" encoding="utf-8" ?>
<!--
  Demonata Gaming Metadata Format ©2025
  Licensed for use under terms in LICENSE.md.
-->
<!--
  ==================================================
  GameStages Modification - Horde Scaling and Spawn Expansion
  @version     1.0.0
  @date        2025-07-15
  @author      Demonata Gaming

  @group       GameStagesSpawnTweaks
  @description
    Increases the spawn count and persistence of Blood Moon and Wandering Hordes
    to maintain pressure and pacing across early to mid-game stages.
  @notes
    - Blood Moon spawn count increased to 128; max alive set to 16.
    - Massive fallback group 'ZombiesAll' appended to Blood Moon stages.
    - Wandering Horde spawn count increased to 30 from GS 1 through 50.
  ==================================================
-->
<configs>
  <!--
  ===============================
  SECTION: BLOODMOON HORDE TWEAKS
  ===============================
  @group      BloodMoonHordeScaling
  @desc       Extends final Blood Moon wave until dawn across all gamestages.
  @version    1.0.0-rc
  @notes
    - Uses XPath patching to set num=99999 and remove duration from final wave.
    - Clean and safe, affects no early-game logic or gamestage behavior.
  -->
  <set xpath="/gamestages/spawner[@name='BloodMoonHorde']/gamestage/spawn[last()]/@num">99999</set>
  <removeattribute xpath="/gamestages/spawner[@name='BloodMoonHorde']/gamestage/spawn[last()]/@duration" />
  <!--
  ===============================
  SECTION: WANDERING HORDE SPAWN INCREASES
  ===============================
  @group    WanderingHordeScaling
  @desc
    Boosts spawn count to 30 across gamestages 1–50 for early game pressure.
  @xref   entitygroups.xml → SECTION: WANDERING HORDE COMPOSITION CHANGES
  -->
  <set xpath="/gamestages/spawner[@name='WanderingHorde']/gamestage[01]/spawn/@num">30</set>
  <set xpath="/gamestages/spawner[@name='WanderingHorde']/gamestage[02]/spawn/@num">30</set>
  <set xpath="/gamestages/spawner[@name='WanderingHorde']/gamestage[03]/spawn/@num">30</set>
  <set xpath="/gamestages/spawner[@name='WanderingHorde']/gamestage[04]/spawn/@num">30</set>
  <set xpath="/gamestages/spawner[@name='WanderingHorde']/gamestage[05]/spawn/@num">30</set>
  <set xpath="/gamestages/spawner[@name='WanderingHorde']/gamestage[06]/spawn/@num">30</set>
  <set xpath="/gamestages/spawner[@name='WanderingHorde']/gamestage[07]/spawn/@num">30</set>
  <set xpath="/gamestages/spawner[@name='WanderingHorde']/gamestage[08]/spawn/@num">30</set>
  <set xpath="/gamestages/spawner[@name='WanderingHorde']/gamestage[09]/spawn/@num">30</set>
  <set xpath="/gamestages/spawner[@name='WanderingHorde']/gamestage[10]/spawn/@num">30</set>
  <set xpath="/gamestages/spawner[@name='WanderingHorde']/gamestage[11]/spawn/@num">30</set>
  <set xpath="/gamestages/spawner[@name='WanderingHorde']/gamestage[12]/spawn/@num">30</set>
  <set xpath="/gamestages/spawner[@name='WanderingHorde']/gamestage[13]/spawn/@num">30</set>
  <set xpath="/gamestages/spawner[@name='WanderingHorde']/gamestage[14]/spawn/@num">30</set>
  <set xpath="/gamestages/spawner[@name='WanderingHorde']/gamestage[15]/spawn/@num">30</set>
  <set xpath="/gamestages/spawner[@name='WanderingHorde']/gamestage[16]/spawn/@num">30</set>
  <set xpath="/gamestages/spawner[@name='WanderingHorde']/gamestage[17]/spawn/@num">30</set>
  <set xpath="/gamestages/spawner[@name='WanderingHorde']/gamestage[18]/spawn/@num">30</set>
  <set xpath="/gamestages/spawner[@name='WanderingHorde']/gamestage[19]/spawn/@num">30</set>
  <set xpath="/gamestages/spawner[@name='WanderingHorde']/gamestage[20]/spawn/@num">30</set>
  <set xpath="/gamestages/spawner[@name='WanderingHorde']/gamestage[21]/spawn/@num">30</set>
  <set xpath="/gamestages/spawner[@name='WanderingHorde']/gamestage[22]/spawn/@num">30</set>
  <set xpath="/gamestages/spawner[@name='WanderingHorde']/gamestage[23]/spawn/@num">30</set>
  <set xpath="/gamestages/spawner[@name='WanderingHorde']/gamestage[24]/spawn/@num">30</set>
  <set xpath="/gamestages/spawner[@name='WanderingHorde']/gamestage[25]/spawn/@num">30</set>
  <set xpath="/gamestages/spawner[@name='WanderingHorde']/gamestage[26]/spawn/@num">30</set>
  <set xpath="/gamestages/spawner[@name='WanderingHorde']/gamestage[27]/spawn/@num">30</set>
  <set xpath="/gamestages/spawner[@name='WanderingHorde']/gamestage[28]/spawn/@num">30</set>
  <set xpath="/gamestages/spawner[@name='WanderingHorde']/gamestage[29]/spawn/@num">30</set>
  <set xpath="/gamestages/spawner[@name='WanderingHorde']/gamestage[30]/spawn/@num">30</set>
  <set xpath="/gamestages/spawner[@name='WanderingHorde']/gamestage[31]/spawn/@num">30</set>
  <set xpath="/gamestages/spawner[@name='WanderingHorde']/gamestage[32]/spawn/@num">30</set>
  <set xpath="/gamestages/spawner[@name='WanderingHorde']/gamestage[33]/spawn/@num">30</set>
  <set xpath="/gamestages/spawner[@name='WanderingHorde']/gamestage[34]/spawn/@num">30</set>
  <set xpath="/gamestages/spawner[@name='WanderingHorde']/gamestage[35]/spawn/@num">30</set>
  <set xpath="/gamestages/spawner[@name='WanderingHorde']/gamestage[36]/spawn/@num">30</set>
  <set xpath="/gamestages/spawner[@name='WanderingHorde']/gamestage[37]/spawn/@num">30</set>
  <set xpath="/gamestages/spawner[@name='WanderingHorde']/gamestage[38]/spawn/@num">30</set>
  <set xpath="/gamestages/spawner[@name='WanderingHorde']/gamestage[39]/spawn/@num">30</set>
  <set xpath="/gamestages/spawner[@name='WanderingHorde']/gamestage[40]/spawn/@num">30</set>
  <set xpath="/gamestages/spawner[@name='WanderingHorde']/gamestage[41]/spawn/@num">30</set>
  <set xpath="/gamestages/spawner[@name='WanderingHorde']/gamestage[42]/spawn/@num">30</set>
  <set xpath="/gamestages/spawner[@name='WanderingHorde']/gamestage[43]/spawn/@num">30</set>
  <set xpath="/gamestages/spawner[@name='WanderingHorde']/gamestage[44]/spawn/@num">30</set>
  <set xpath="/gamestages/spawner[@name='WanderingHorde']/gamestage[45]/spawn/@num">30</set>
  <set xpath="/gamestages/spawner[@name='WanderingHorde']/gamestage[46]/spawn/@num">30</set>
  <set xpath="/gamestages/spawner[@name='WanderingHorde']/gamestage[47]/spawn/@num">30</set>
  <set xpath="/gamestages/spawner[@name='WanderingHorde']/gamestage[48]/spawn/@num">30</set>
  <set xpath="/gamestages/spawner[@name='WanderingHorde']/gamestage[49]/spawn/@num">30</set>
  <set xpath="/gamestages/spawner[@name='WanderingHorde']/gamestage[50]/spawn/@num">30</set>
</configs>
